[
	{
		"name": "弥彦山",
		"pref": 15 ,
		"code": "15150001",
		"url": "http://tenkura.n-kishou.co.jp/tk/kanko/kad.html?code=15150001&amp;type=15&amp;ba=hr"
	},
	{
		"name": "妙高高原",
		"pref": 15 ,
		"code": "15150002",
		"url": "http://tenkura.n-kishou.co.jp/tk/kanko/kad.html?code=15150002&amp;type=15&amp;ba=hr"
	},
	{
		"name": "越後湯沢",
		"pref": 15 ,
		"code": "15150003",
		"url": "http://tenkura.n-kishou.co.jp/tk/kanko/kad.html?code=15150003&amp;type=15&amp;ba=hr"
	},
	{
		"name": "苗場",
		"pref": 15 ,
		"code": "15150004",
		"url": "http://tenkura.n-kishou.co.jp/tk/kanko/kad.html?code=15150004&amp;type=15&amp;ba=hr"
	},
	{
		"name": "妙高山",
		"pref": "15" ,
		"code": "15150005",
		"url": "http://tenkura.n-kishou.co.jp/tk/kanko/kad.html?code=15150005&amp;type=15&amp;ba=hr"
	},
	{
		"name": "火打山",
		"pref": 15 ,
		"code": "15150006",
		"url": "http://tenkura.n-kishou.co.jp/tk/kanko/kad.html?code=15150006&amp;type=15&amp;ba=hr"
	},
	{
		"name": "越後駒ヶ岳",
		"pref": 15 ,
		"code": "15150007",
		"url": "http://tenkura.n-kishou.co.jp/tk/kanko/kad.html?code=15150007&amp;type=15&amp;ba=hr"
	},
	{
		"name": "平ヶ岳",
		"pref": 15 ,
		"code": "15150008",
		"url": "http://tenkura.n-kishou.co.jp/tk/kanko/kad.html?code=15150008&amp;type=15&amp;ba=hr"
	},
	{
		"name": "巻機山",
		"pref": 15 ,
		"code": "15150009",
		"url": "http://tenkura.n-kishou.co.jp/tk/kanko/kad.html?code=15150009&amp;type=15&amp;ba=hr"
	},
	{
		"name": "二王子岳",
		"pref": 15 ,
		"code": "15150010",
		"url": "http://tenkura.n-kishou.co.jp/tk/kanko/kad.html?code=15150010&amp;type=15&amp;ba=hr"
	},
	{
		"name": "御神楽岳",
		"pref": 15 ,
		"code": "15150011",
		"url": "http://tenkura.n-kishou.co.jp/tk/kanko/kad.html?code=15150011&amp;type=15&amp;ba=hr"
	},
	{
		"name": "八海山",
		"pref": 15 ,
		"code": "15150012",
		"url": "http://tenkura.n-kishou.co.jp/tk/kanko/kad.html?code=15150012&amp;type=15&amp;ba=hr"
	},
	{
		"name": "えぶり差岳",
		"pref": 15 ,
		"code": "15150013",
		"url": "http://tenkura.n-kishou.co.jp/tk/kanko/kad.html?code=15150013&amp;type=15&amp;ba=hr"
	},
	{
		"name": "苗場山",
		"pref": 15 ,
		"code": "15150015",
		"url": "http://tenkura.n-kishou.co.jp/tk/kanko/kad.html?code=15150015&amp;type=15&amp;ba=hr"
	},
	{
		"name": "小蓮華山",
		"pref": 15 ,
		"code": "15150016",
		"url": "http://tenkura.n-kishou.co.jp/tk/kanko/kad.html?code=15150016&amp;type=15&amp;ba=hr"
	},
	{
		"name": "守門岳",
		"pref": 15 ,
		"code": "15150017",
		"url": "http://tenkura.n-kishou.co.jp/tk/kanko/kad.html?code=15150017&amp;type=15&amp;ba=hr"
	},
	{
	"name": "坂戸山",
	"pref": 15 ,
	"code": "15150018",
	"url": "http://tenkura.n-kishou.co.jp/tk/kanko/kad.html?code=15150018&amp;type=15&amp;ba=hr"
	},
	{
		"name": "金北山",
		"pref": 15 ,
		"code": "15150019",
		"url": "http://tenkura.n-kishou.co.jp/tk/kanko/kad.html?code=15150019&amp;type=15&amp;ba=hr"
	},
	{
	"name": "鳴倉山",
	"pref": 15 ,
	"code": "15150020",
	"url": "http://tenkura.n-kishou.co.jp/tk/kanko/kad.html?code=15150020&amp;type=15&amp;ba=hr"
	},
	{
		"name": "仙ノ倉山",
		"pref": 15 ,
		"code": "15150021",
		"url": "http://tenkura.n-kishou.co.jp/tk/kanko/kad.html?code=15150021&amp;type=15&amp;ba=hr"
	},
	{
		"name": "浅草岳",
		"pref": 15 ,
		"code": "15150022",
		"url": "http://tenkura.n-kishou.co.jp/tk/kanko/kad.html?code=15150022&amp;type=15&amp;ba=hr"
	},
	{
		"name": "粟ヶ岳",
		"pref": 15 ,
		"code": "15150023",
		"url": "http://tenkura.n-kishou.co.jp/tk/kanko/kad.html?code=15150023&amp;type=15&amp;ba=hr"
	},
	{
	"name": "米山",
	"pref": 15 ,
	"code": "15150024",
	"url": "http://tenkura.n-kishou.co.jp/tk/kanko/kad.html?code=15150024&amp;type=15&amp;ba=hr"
	},
	{
		"name": "大源太山",
		"pref": 15 ,
		"code": "15150025",
		"url": "http://tenkura.n-kishou.co.jp/tk/kanko/kad.html?code=15150025&amp;type=15&amp;ba=hr"
	},
	{
	"name": "五頭山",
	"pref": 15 ,
	"code": "15150026",
	"url": "http://tenkura.n-kishou.co.jp/tk/kanko/kad.html?code=15150026&amp;type=15&amp;ba=hr"
	},
	{
		"name": "新潟焼山",
		"pref": 15 ,
		"code": "15150027",
		"url": "http://tenkura.n-kishou.co.jp/tk/kanko/kad.html?code=15150027&amp;type=15&amp;ba=hr"
	},
	{
		"name": "大日岳",
		"pref": 15 ,
		"code": "15150028",
		"url": "http://tenkura.n-kishou.co.jp/tk/kanko/kad.html?code=15150028&amp;type=15&amp;ba=hr"
	},
	{
		"name": "神楽ケ峰",
		"pref": 15 ,
		"code": "15150029",
		"url": "http://tenkura.n-kishou.co.jp/tk/kanko/kad.html?code=15150029&amp;type=15&amp;ba=hr"
	},
	{
		"name": "粟立山",
		"pref": 15 ,
		"code": "15150030",
		"url": "http://tenkura.n-kishou.co.jp/tk/kanko/kad.html?code=15150030&amp;type=15&amp;ba=hr"
	},
	{
	"name": "ドンデン山",
	"pref": 15 ,
	"code": "15150031",
	"url": "http://tenkura.n-kishou.co.jp/tk/kanko/kad.html?code=15150031&amp;type=15&amp;ba=hr"
	},
	{
		"name": "阿寺山",
		"pref": 15 ,
		"code": "15150032",
		"url": "http://tenkura.n-kishou.co.jp/tk/kanko/kad.html?code=15150032&amp;type=15&amp;ba=hr"
	},
	{
		"name": "白山",
		"pref": 15 ,
		"code": "15150033",
		"url": "http://tenkura.n-kishou.co.jp/tk/kanko/kad.html?code=15150033&amp;type=15&amp;ba=hr"
	},
	{
	"name": "大蔵山",
	"pref": 15 ,
	"code": "15150034",
	"url": "http://tenkura.n-kishou.co.jp/tk/kanko/kad.html?code=15150034&amp;type=15&amp;ba=hr"
	},
	{
	"name": "菅名岳",
	"pref": 15 ,
	"code": "15150035",
	"url": "http://tenkura.n-kishou.co.jp/tk/kanko/kad.html?code=15150035&amp;type=15&amp;ba=hr"
	},
	{
	"name": "菱ヶ岳",
	"pref": 15 ,
	"code": "15150036",
	"url": "http://tenkura.n-kishou.co.jp/tk/kanko/kad.html?code=15150036&amp;type=15&amp;ba=hr"
	},
	{
		"name": "高津倉山",
		"pref": 15 ,
		"code": "15150037",
		"url": "http://tenkura.n-kishou.co.jp/tk/kanko/kad.html?code=15150037&amp;type=15&amp;ba=hr"
	},
	{
		"name": "鉾ヶ岳",
		"pref": 15 ,
		"code": "15150038",
		"url": "http://tenkura.n-kishou.co.jp/tk/kanko/kad.html?code=15150038&amp;type=15&amp;ba=hr"
	},
	{
	"name": "光兎山",
	"pref": 15 ,
	"code": "15150039",
	"url": "http://tenkura.n-kishou.co.jp/tk/kanko/kad.html?code=15150039&amp;type=15&amp;ba=hr"
	},
	{
		"name": "北股岳",
		"pref": 15 ,
		"code": "15150040",
		"url": "http://tenkura.n-kishou.co.jp/tk/kanko/kad.html?code=15150040&amp;type=15&amp;ba=hr"
	},
	{
		"name": "飯豊山",
		"pref": 7,
		"code:": "7150003",
		"url": "http://tenkura.n-kishou.co.jp/tk/kanko/kad.html?code=07150003&amp;type=15&amp;ba=hr"
	},
	{
		"name": "雨飾山",
		"pref": 20 ,
		"code": "20150040",
		"url": "http://tenkura.n-kishou.co.jp/tk/kanko/kad.html?code=20150040&amp;type=15&amp;ba=hr"
	}
]